annobee/__init__.py
annobee/cli.py
annobee/config.py
annobee/criterias.py
annobee/utils.py
annobee/variant.py
annobee-0.6.1.dist-info/LICENSE
annobee-0.6.1.dist-info/METADATA
annobee-0.6.1.dist-info/WHEEL
annobee-0.6.1.dist-info/entry_points.txt
annobee-0.6.1.dist-info/top_level.txt
annobee-0.6.1.dist-info/RECORD
