Metadata-Version: 2.1
Name: annobee
Version: 0.6.1
Summary: UNKNOWN
Home-page: https://github.com/variantAnnotation/annobee-sdk
License: UNKNOWN
Platform: UNKNOWN
Classifier: Programming Language :: Python :: 3
Classifier: License :: OSI Approved :: MIT License
Classifier: Operating System :: OS Independent
Requires-Python: >=3.6
License-File: LICENSE
Requires-Dist: dnspython
Requires-Dist: numpy
Requires-Dist: pandas
Requires-Dist: pool
Requires-Dist: pymongo
Requires-Dist: python-dateutil
Requires-Dist: pytz
Requires-Dist: requests
Requires-Dist: six
Requires-Dist: tqdm
Requires-Dist: tzdata
